atom/__init__.py
atom/api.py
atom/base.py
atom/cli.py
atom/config.py
atom/manager.py
atom/scheduler.py
atom/utils.py
atom/data/test.txt
atom/data/test_decorator.py
atom/data/test_df_to_html.py
atom/data/test_dill.py
atom/data/test_main.py
atom/data/test_minio.py
atom/data/test_pkgpath.py
atom/data/test_scheduler.py
atom/data/test_yaml.py
atom/data/test_zero.py
atom/data/test/atom.db
atom/data/test/atom_config.yaml
atom/data/test/data/merge_data_GDTYUAN_ec.csv
atom/doc/README.mdown
atom/static/atomsymbol.JPG
atom/static/dataui.JPG
atom/static/shields_author.svg
atom/static/shields_license.svg
atom/static/shields_python.svg
atom/static/shields_version.svg
atom/static/webui.JPG
atom/static/如何为function添加新的魔法方法python_百度搜索.html
atom/static/Design/Dia/AtomUML.dia
atom/static/Design/Dia/AtomUML.dia~
atom/static/Design/Dia/AtomUML.png
atom/static/Design/Dia/AtomUML.svg
atom/static/OfficialDoc/doc/Makefile
atom/static/OfficialDoc/doc/make.bat
atom/static/OfficialDoc/doc/build/doctrees/environment.pickle
atom/static/OfficialDoc/doc/build/doctrees/index.doctree
atom/static/OfficialDoc/doc/build/doctrees/介绍.doctree
atom/static/OfficialDoc/doc/build/doctrees/安装.doctree
atom/static/OfficialDoc/doc/build/doctrees/快速指南.doctree
atom/static/OfficialDoc/doc/build/doctrees/设计.doctree
atom/static/OfficialDoc/doc/build/html/.buildinfo
atom/static/OfficialDoc/doc/build/html/genindex.html
atom/static/OfficialDoc/doc/build/html/index.html
atom/static/OfficialDoc/doc/build/html/objects.inv
atom/static/OfficialDoc/doc/build/html/search.html
atom/static/OfficialDoc/doc/build/html/searchindex.js
atom/static/OfficialDoc/doc/build/html/介绍.html
atom/static/OfficialDoc/doc/build/html/安装.html
atom/static/OfficialDoc/doc/build/html/快速指南.html
atom/static/OfficialDoc/doc/build/html/设计.html
atom/static/OfficialDoc/doc/build/html/_images/AtomUML.png
atom/static/OfficialDoc/doc/build/html/_sources/index.rst.txt
atom/static/OfficialDoc/doc/build/html/_sources/介绍.rst.txt
shihua_atom-0.1.1.dist-info/LICENSE
shihua_atom-0.1.1.dist-info/METADATA
shihua_atom-0.1.1.dist-info/WHEEL
shihua_atom-0.1.1.dist-info/entry_points.txt
shihua_atom-0.1.1.dist-info/top_level.txt
shihua_atom-0.1.1.dist-info/RECORD
