Metadata-Version: 2.1
Name: shihua-atom
Version: 0.1.1
Summary: Atom is a feature engineering tool.
Home-page: https://github.com/redblue0216/Atom
Author: shihua
Author-email: 15021408795@163.com
License: MIT
Platform: UNKNOWN
Requires-Python: >=3.9.12
License-File: LICENSE
